recon3d/__init__.py
recon3d/command_line.py
recon3d/constants.py
recon3d/downscale.py
recon3d/grayscale_image_stack_to_segmentation.py
recon3d/hdf_io.py
recon3d/image_stack_to_array.py
recon3d/instance_analysis.py
recon3d/npy_to_mesh.py
recon3d/static_test_paths.py
recon3d/types.py
recon3d/utility.py
recon3d-2.0.6.dist-info/licenses/LICENSE
recon3d-2.0.6.dist-info/licenses/NOTICE.md
recon3d-2.0.6.dist-info/METADATA
recon3d-2.0.6.dist-info/WHEEL
recon3d-2.0.6.dist-info/entry_points.txt
recon3d-2.0.6.dist-info/top_level.txt
recon3d-2.0.6.dist-info/RECORD
